{
	"SoftwareRoles": [
		{
			"label": {
				"en_GB": "Architecture",
				"fr_FR": "Architecture"
			},
			"value": "Architecture"
		},
		{
			"label": {
				"en_GB": "Design",
				"fr_FR": "Conception"
			},
			"value": "Conception"
		},
		{
			"label": {
				"en_GB": "Debugging",
				"fr_FR": "Débogage"
			},
			"value": "Débogage"
		},
		{
			"label": {
				"en_GB": "Development",
				"fr_FR": "Développement"
			},
			"value": "Développement"
		},
		{
			"label": {
				"en_GB": "Documentation",
				"fr_FR": "Documentation"
			},
			"value": "Documentation"
		},
		{
			"label": {
				"en_GB": "Maintenance",
				"fr_FR": "Maintenance"
			},
			"value": "Maintenance"
		},
		{
			"label": {
				"en_GB": "Management",
				"fr_FR": "Management"
			},
			"value": "Management"
		},
		{
			"label": {
				"en_GB": "Support",
				"fr_FR": "Support"
			},
			"value": "Support"
		},
		{
			"label": {
				"en_GB": "Test",
				"fr_FR": "Test"
			},
			"value": "Test"
		},
		{
			"label": {
				"fr_FR": "Tous les rôles",
				"en_GB": "All roles"
			},
			"value": "Architecture, Conception, Débogage, Développement, Documentation, Maintenance, Management, Support, Test"
		},
		{
			"label": {
				"en_GB": "Other",
				"fr_FR": "Autre"
			},
			"value": "Autre"
		}
	]
}